PhyweControl/__init__.py
PhyweControl/command_values.py
PhyweControl/function_generator.py
PhyweControl/function_generator_phywe.py
phywecontrol-1.0.0.dist-info/licenses/LICENSE
phywecontrol-1.0.0.dist-info/METADATA
phywecontrol-1.0.0.dist-info/WHEEL
phywecontrol-1.0.0.dist-info/top_level.txt
phywecontrol-1.0.0.dist-info/RECORD
