Metadata-Version: 2.4
Name: phywecontrol
Version: 1.0.0
Summary: A Package to control a digital function generator by PHYWE
License-Expression: GPL-2.0
Project-URL: Homepage, https://github.com/Schallform/PhyweControl
Classifier: Programming Language :: Python :: 3
Classifier: Operating System :: OS Independent
Requires-Python: >=3.6
License-File: LICENSE
Dynamic: license-file
